Metadata-Version: 1.1
Name: python-bsn-neutronclient
Version: 12.0.0
Summary: Python bindings for Big Switch Networks Neutron API
Home-page: http://www.bigswitch.com/
Author: Big Switch Networks
Author-email: support@bigswitch.com
License: ASL 2.0
Platform: UNKNOWN
Classifier: Environment :: OpenStack
Classifier: Intended Audience :: Information Technology
Classifier: Intended Audience :: System Administrators
Classifier: License :: OSI Approved :: Apache Software License
Classifier: Operating System :: POSIX :: Linux
Classifier: Programming Language :: Python
Classifier: Programming Language :: Python :: 2
Classifier: Programming Language :: Python :: 2.7
Classifier: Programming Language :: Python :: 3
Classifier: Programming Language :: Python :: 3.5
